[{"Uuid":"a1a0bef1-3617-46d7-a838-d513fb364a7f","Name":"Bitcoin ledger","Coin":"BTC","CoinAmount":0.125,"AccountCategory":"Ledger"},{"Uuid":"f2c28625-f046-4959-b5d4-59efaa6bd5fd","Name":"Bitcoin Binance","Coin":"BTC","CoinAmount":0.3324,"AccountCategory":"Binance"},{"Uuid":"965e28fe-4813-4d9b-b610-76b0c2b3efb7","Name":"Ethereum Main","Coin":"ETH","CoinAmount":6.25,"AccountCategory":"Ledger"},{"Uuid":"708cb1ab-260b-4cae-a975-6e232ab5cc80","Name":"XRP Main","Coin":"XRP","CoinAmount":5000.0,"AccountCategory":"Ledger"}]